terrascope_api/__init__.py
terrascope_api/async_client.py
terrascope_api/async_interceptors.py
terrascope_api/sync_client.py
terrascope_api/terrascope_base_api.py
terrascope_api/models/__init__.py
terrascope_api/models/algorithm_computation_execution_pb2.py
terrascope_api/models/algorithm_computation_execution_pb2.pyi
terrascope_api/models/algorithm_computation_pb2.py
terrascope_api/models/algorithm_computation_pb2.pyi
terrascope_api/models/algorithm_config_pb2.py
terrascope_api/models/algorithm_config_pb2.pyi
terrascope_api/models/algorithm_manifest_pb2.py
terrascope_api/models/algorithm_manifest_pb2.pyi
terrascope_api/models/algorithm_pb2.py
terrascope_api/models/algorithm_pb2.pyi
terrascope_api/models/algorithm_version_pb2.py
terrascope_api/models/algorithm_version_pb2.pyi
terrascope_api/models/analysis_computation_pb2.py
terrascope_api/models/analysis_computation_pb2.pyi
terrascope_api/models/analysis_config_pb2.py
terrascope_api/models/analysis_config_pb2.pyi
terrascope_api/models/analysis_pb2.py
terrascope_api/models/analysis_pb2.pyi
terrascope_api/models/analysis_version_pb2.py
terrascope_api/models/analysis_version_pb2.pyi
terrascope_api/models/aoi_catalog_pb2.py
terrascope_api/models/aoi_catalog_pb2.pyi
terrascope_api/models/aoi_collection_pb2.py
terrascope_api/models/aoi_collection_pb2.pyi
terrascope_api/models/aoi_export_pb2.py
terrascope_api/models/aoi_export_pb2.pyi
terrascope_api/models/aoi_pb2.py
terrascope_api/models/aoi_pb2.pyi
terrascope_api/models/aoi_transaction_pb2.py
terrascope_api/models/aoi_transaction_pb2.pyi
terrascope_api/models/aoi_version_pb2.py
terrascope_api/models/aoi_version_pb2.pyi
terrascope_api/models/common_models_pb2.py
terrascope_api/models/common_models_pb2.pyi
terrascope_api/models/credit_pb2.py
terrascope_api/models/credit_pb2.pyi
terrascope_api/models/data_source_pb2.py
terrascope_api/models/data_source_pb2.pyi
terrascope_api/models/data_tracking_pb2.py
terrascope_api/models/data_tracking_pb2.pyi
terrascope_api-2025.10.82308.dist-info/licenses/LICENSE
terrascope_api-2025.10.82308.dist-info/METADATA
terrascope_api-2025.10.82308.dist-info/WHEEL
terrascope_api-2025.10.82308.dist-info/top_level.txt
terrascope_api-2025.10.82308.dist-info/RECORD
