Metadata-Version: 2.4
Name: terrascope-api
Version: 2025.10.82308
Summary: Terrascope API Client
License-File: LICENSE
Requires-Dist: grpcio
Requires-Dist: grpcio-status
Requires-Dist: requests
Dynamic: license-file
Dynamic: requires-dist
Dynamic: summary
